eessi/__init__.py
eessi/cli/check.py
eessi/cli/init.py
eessi/cli/main.py
eessi/cli/shell.py
eessi-0.0.5.dist-info/licenses/LICENSE
eessi-0.0.5.dist-info/METADATA
eessi-0.0.5.dist-info/WHEEL
eessi-0.0.5.dist-info/entry_points.txt
eessi-0.0.5.dist-info/top_level.txt
eessi-0.0.5.dist-info/RECORD
