Metadata-Version: 2.4
Name: eessi
Version: 0.0.5
Summary: User-friendly command line interface to EESSI - https://eessi.io
Author: Kenneth Hoste
License:                     GNU GENERAL PUBLIC LICENSE
Requires-Python: >=3.9
License-File: LICENSE
Requires-Dist: typer>=0.21
Requires-Dist: rich>=14.0
Dynamic: license-file
